fibonachi/__init__.py
fibonachi/exemple.py
Quzi-0.0.2.dist-info/LICENSE.txt
Quzi-0.0.2.dist-info/METADATA
Quzi-0.0.2.dist-info/WHEEL
Quzi-0.0.2.dist-info/top_level.txt
Quzi-0.0.2.dist-info/RECORD
