Metadata-Version: 2.1
Name: Quzi
Version: 0.0.2
Summary: quzi 4
Author: Devid Zurabashvili
Author-email: david.zurabashvili.1@btu.edu.ge
Classifier: Programming Language :: Python :: 3
Classifier: License :: OSI Approved :: MIT License
Classifier: Operating System :: OS Independent
Requires-Python: >=3.6
License-File: LICENSE.txt
